af_ibov_downloader/__init__.py
af_ibov_downloader/archive.py
af_ibov_downloader/cli.py
af_ibov_downloader/download.py
af_ibov_downloader/errors.py
af_ibov_downloader/handlers.py
af_ibov_downloader/version.py
af_ibov_downloader-0.1.1.dist-info/entry_points.txt
af_ibov_downloader-0.1.1.dist-info/LICENSE.md
af_ibov_downloader-0.1.1.dist-info/WHEEL
af_ibov_downloader-0.1.1.dist-info/METADATA
af_ibov_downloader-0.1.1.dist-info/RECORD
