Metadata-Version: 2.1
Name: af-ibov-downloader
Version: 0.1.1
Summary: A CLI tool to download market data from ibovespa
Home-page: https://af-ibov-downloader.readthedocs.io/en/latest/
License: MIT
Author: Leonardo Rossetti
Author-email: me@lrossetti.com
Requires-Python: >=3.9,<4.0
Classifier: License :: OSI Approved :: MIT License
Classifier: Programming Language :: Python :: 3
Classifier: Programming Language :: Python :: 3.9
Requires-Dist: requests (>=2.25.1,<3.0.0)
Project-URL: Repository, https://gitlab.com/aerofin/tooling/af-ibov-downloader
